labpack/__init__.py
labpack/activity/__init__.py
labpack/activity/moves.py
labpack/authentication/__init__.py
labpack/authentication/oauth2.py
labpack/authentication/ssl.py
labpack/authentication/aws/__init__.py
labpack/authentication/aws/iam-rules.json
labpack/authentication/aws/iam.py
labpack/authentication/aws/update.py
labpack/banking/__init__.py
labpack/banking/capitalone.py
labpack/compilers/__init__.py
labpack/compilers/drep.py
labpack/compilers/encoding.py
labpack/compilers/filters.py
labpack/compilers/git.py
labpack/compilers/json.py
labpack/compilers/objects.py
labpack/compilers/yaml.py
labpack/databases/__init__.py
labpack/databases/cassandra.py
labpack/databases/couchbase.py
labpack/databases/sql.py
labpack/databases/google/__init__.py
labpack/databases/google/datastore.py
labpack/databases/models/sync-gateway-public.json
labpack/databases/models/sync_function.js
labpack/datasets/__init__.py
labpack/datasets/iso_3166.py
labpack/datasets/iso_3166_2_US.py
labpack/email/__init__.py
labpack/email/mailgun.py
labpack/email/mandrill.py
labpack/encryption/__init__.py
labpack/encryption/cryptolab.py
labpack/events/__init__.py
labpack/events/meetup.py
labpack/handlers/__init__.py
labpack/handlers/requests.py
labpack/location/__init__.py
labpack/location/find.py
labpack/mapping/__init__.py
labpack/mapping/data.py
labpack/messaging/__init__.py
labpack/messaging/telegram.py
labpack/messaging/twilio.py
labpack/parsing/__init__.py
labpack/parsing/comparison.py
labpack/parsing/conversion.py
labpack/parsing/flask.py
labpack/parsing/grammar.py
labpack/parsing/magic.py
labpack/parsing/regex.py
labpack/parsing/shell.py
labpack/performance/__init__.py
labpack/performance/performlab.py
labpack/platforms/__init__.py
labpack/platforms/apscheduler.py
labpack/platforms/docker.py
labpack/platforms/heroku.py
labpack/platforms/localhost.py
labpack/platforms/aws/__init__.py
labpack/platforms/aws/ec2-rules.json
labpack/platforms/aws/ec2.py
labpack/platforms/aws/r53.py
labpack-0.23.dist-info/LICENSE.txt
labpack-0.23.dist-info/METADATA
labpack-0.23.dist-info/WHEEL
labpack-0.23.dist-info/top_level.txt
labpack-0.23.dist-info/RECORD
