Metadata-Version: 2.1
Name: labpack
Version: 0.23
Summary: UNKNOWN
Home-page: https://github.com/collectiveacuity/labPack
Author: rcj1492
Author-email: support@collectiveacuity.com
Maintainer-email: support@collectiveacuity.com
License: MIT
Platform: UNKNOWN
Classifier: Development Status :: 3 - Alpha
Classifier: Environment :: Web Environment
Classifier: Intended Audience :: Developers
Classifier: License :: OSI Approved :: MIT License
Classifier: Natural Language :: English
Classifier: Programming Language :: Python
Classifier: Programming Language :: Python :: 3.5
Requires-Dist: pytz (>=2015.7)
Requires-Dist: tzlocal (>=1.2)
Requires-Dist: python-dateutil (>=2.4.2)
Requires-Dist: pyyaml (>=5.1)
Requires-Dist: jsonmodel
Requires-Dist: requests
Requires-Dist: PyJWT (>=1.4.2)
